{
  "gitSyncId": "679b4eb98d92e06dbbd9424c_14d63ae8-2ac1-49b2-83a4-7b60e50495e2",
  "id": "Page1_InsertQuery",
  "pluginId": "mongo-plugin",
  "pluginType": "DB",
  "unpublishedAction": {
    "actionConfiguration": {
      "encodeParamsToggle": true,
      "formData": {
        "collection": {
          "componentData": "movies",
          "data": "movies",
          "viewType": "component"
        },
        "command": {
          "componentData": "INSERT",
          "data": "INSERT",
          "viewType": "component"
        },
        "insert": {
          "documents": {
            "componentData": "{\n \"genres\": {{insert_col_input1.text}}, \n \"homepage\": {{insert_col_input2.text}}, \n \"imdb_id\": {{insert_col_input3.text}}, \n \"poster_path\": {{insert_col_input4.text}}\n}",
            "data": "{{insert_form.formData}}",
            "viewType": "component"
          }
        },
        "misc": {
          "formToNativeQuery": {
            "data": "{\n  \"insert\": \"movies\",\n  \"documents\": {{insert_form.formData}}\n}\n",
            "status": "SUCCESS"
          }
        },
        "smartSubstitution": {
          "componentData": true,
          "data": true,
          "viewType": "component"
        }
      },
      "paginationType": "NONE",
      "timeoutInMillisecond": 10000
    },
    "confirmBeforeExecute": false,
    "datasource": {
      "id": "Movies",
      "isAutoGenerated": false,
      "name": "Movies",
      "pluginId": "mongo-plugin"
    },
    "name": "InsertQuery",
    "pageId": "Page1",
    "runBehaviour": "MANUAL",
    "userSetOnLoad": false
  }
}